color_extractor/__init__.py
color_extractor/extractor.py
tests/__init__.py
tests/test_extractor.py
rafidimg-0.1.dist-info/METADATA
rafidimg-0.1.dist-info/WHEEL
rafidimg-0.1.dist-info/top_level.txt
rafidimg-0.1.dist-info/RECORD
